{
"applications": [
        {
            "id": 1,
            "applicationId": 1,
            "applicationCode": "code 1",
            "liveCode": "livecode",
            "judgeTeam": "team 1",
            "fieldvalues": [
                {
                    "type": "TextField",
                    "name": "Text field 1",
                    "value": "value 1"
                },
                {
                    "type": "ListField",
                    "name": "List field 1",
                    "value": "value 1",
                    "values": [
                        "value 1",
                        "value 2",
                        "value 3"
                    ]
                },
                {
                    "type": "ListField",
                    "name": "List field 2",
                    "value": { "id": 1, "name": "Country 1" },
                    "values": [
                        { "id": 1, "name": "Country 1" },
                        { "id": 2, "name": "Country 2" },
                        { "id": 3, "name": "Country 3" }
                    ]
                },
                {
                    "type": "TextField",
                    "name": "Text field 2",
                    "value": "value 2"
                }
            ]
        },
        {
            "id": 2,
            "applicationId": 2,
            "applicationCode": "code 2",
            "liveCode": "livecode",
            "judgeTeam": "team 2",
            "fieldvalues": [
                {
                    "type": "TextField",
                    "name": "Text field 1",
                    "value": "value 1"
                }
            ]
        }
    ]
}
